server_lib/__init__.py
server_lib/simple.py
ds_server_lib-6.0.0.dist-info/METADATA
ds_server_lib-6.0.0.dist-info/WHEEL
ds_server_lib-6.0.0.dist-info/top_level.txt
ds_server_lib-6.0.0.dist-info/RECORD
