Metadata-Version: 2.4
Name: ds-server-lib
Version: 6.0.0
Summary: Server library for owasp depscan
Author-email: Team AppThreat <cloud@appthreat.com>
License-Expression: MIT
Project-URL: Homepage, https://github.com/owasp-dep-scan/dep-scan
Project-URL: Bug-Tracker, https://github.com/owasp-dep-scan/dep-scan/issues
Project-URL: Funding, https://owasp.org/donate/?reponame=www-project-dep-scan&title=OWASP+depscan
Classifier: Development Status :: 5 - Production/Stable
Classifier: Intended Audience :: Developers
Classifier: Intended Audience :: System Administrators
Classifier: Operating System :: OS Independent
Classifier: Programming Language :: Python :: 3.10
Classifier: Programming Language :: Python :: 3.11
Classifier: Programming Language :: Python :: 3.12
Classifier: Programming Language :: Python :: 3.13
Classifier: Topic :: Security
Classifier: Topic :: Utilities
Requires-Python: >=3.10
Requires-Dist: appthreat-vulnerability-db>=6.4.4
Requires-Dist: custom-json-diff>=2.1.6
Requires-Dist: quart>=0.20.0
Requires-Dist: rich>=13.9.4
Requires-Dist: ds-analysis-lib
Provides-Extra: dev
Requires-Dist: pytest>=8.3.4; extra == "dev"
Requires-Dist: pytest-asyncio>=1.2.0; extra == "dev"
Requires-Dist: pytest-cov>=6.0.0; extra == "dev"
